{"_ts":[1556713214],"_r":{"breakdown":{"html":{"bytes":[12004],"requests":[3]},"js":{"bytes":[535364],"requests":[4]},"css":{"bytes":[36736],"requests":[1]},"image":{"bytes":[137],"requests":[3]},"flash":{"bytes":[0],"requests":[0]},"font":{"bytes":[0],"requests":[0]},"video":{"bytes":[0],"requests":[0]},"other":{"bytes":[650],"requests":[4]}},"date":[1556713214],"domElements":[1410],"domInteractive":[1358],"firstPaint":[0],"fullyLoaded":[5126],"id":["190501_KS_f76cdd54645af09aadd386726013def4"],"loadTime":[1849],"render":[0],"SpeedIndex":[0],"TTFB":[235],"videoFrames":[[{"_i":"ms_000000.jpg","_t":0,"_vc":100}]],"visualComplete":[0],"lighthouse":[19],"pagespeed":[50]}}