{"_ts":[1546319752,1546406361],"_r":{"breakdown":{"html":{"bytes":[565572,565572],"requests":[15,14]},"js":{"bytes":[1283894,1283782],"requests":[61,61]},"css":{"bytes":[133538,133538],"requests":[30,30]},"image":{"bytes":[1955115,1944163],"requests":[56,54]},"flash":{"bytes":[11160,11160],"requests":[1,1]},"font":{"bytes":[368955,368955],"requests":[16,16]},"video":{"bytes":[0,0],"requests":[0,0]},"other":{"bytes":[1165085,1158963],"requests":[26,24]}},"date":[1546319752,1546406361],"domElements":[911,907],"domInteractive":[1750,1921],"firstPaint":[1805.1999999998,1944.6000000025],"fullyLoaded":[14145,12609],"id":["190101_Y3_126e4af69dd33f3e738c7a2d58f629bf","190102_PQ_5b8b0caa7981cc9b36ef7aec2d00ce70"],"loadTime":[5289,4548],"render":[1800,2000],"SpeedIndex":[2763,2740],"TTFB":[175,198],"videoFrames":[[{"_i":"ms_000000.jpg","_t":0,"_vc":0},{"_i":"ms_001800.jpg","_t":1800,"_vc":37},{"_i":"ms_001900.jpg","_t":1900,"_vc":37},{"_i":"ms_002000.jpg","_t":2000,"_vc":37},{"_i":"ms_002100.jpg","_t":2100,"_vc":37},{"_i":"ms_002200.jpg","_t":2200,"_vc":68},{"_i":"ms_002300.jpg","_t":2300,"_vc":68},{"_i":"ms_002600.jpg","_t":2600,"_vc":69},{"_i":"ms_002700.jpg","_t":2700,"_vc":68},{"_i":"ms_003300.jpg","_t":3300,"_vc":68},{"_i":"ms_003400.jpg","_t":3400,"_vc":68},{"_i":"ms_003500.jpg","_t":3500,"_vc":68},{"_i":"ms_003600.jpg","_t":3600,"_vc":68},{"_i":"ms_004000.jpg","_t":4000,"_vc":71},{"_i":"ms_004200.jpg","_t":4200,"_vc":71},{"_i":"ms_004400.jpg","_t":4400,"_vc":80},{"_i":"ms_004500.jpg","_t":4500,"_vc":100}],[{"_i":"ms_000000.jpg","_t":0,"_vc":0},{"_i":"ms_002000.jpg","_t":2000,"_vc":44},{"_i":"ms_002100.jpg","_t":2100,"_vc":44},{"_i":"ms_002200.jpg","_t":2200,"_vc":44},{"_i":"ms_002300.jpg","_t":2300,"_vc":44},{"_i":"ms_002400.jpg","_t":2400,"_vc":44},{"_i":"ms_002500.jpg","_t":2500,"_vc":75},{"_i":"ms_002600.jpg","_t":2600,"_vc":75},{"_i":"ms_003000.jpg","_t":3000,"_vc":76},{"_i":"ms_003100.jpg","_t":3100,"_vc":76},{"_i":"ms_003200.jpg","_t":3200,"_vc":76},{"_i":"ms_003300.jpg","_t":3300,"_vc":76},{"_i":"ms_003400.jpg","_t":3400,"_vc":76},{"_i":"ms_003500.jpg","_t":3500,"_vc":76},{"_i":"ms_003600.jpg","_t":3600,"_vc":76},{"_i":"ms_003900.jpg","_t":3900,"_vc":78},{"_i":"ms_004300.jpg","_t":4300,"_vc":83},{"_i":"ms_004400.jpg","_t":4400,"_vc":93},{"_i":"ms_004600.jpg","_t":4600,"_vc":100}]],"visualComplete":[4500,4600],"lighthouse":[57,57],"pagespeed":[72,72]}}